nanopyfw/__init__.py
nanopyfw/base.py
nanopyfw/jitfunctions.py
nanopyfw/examples/__init__.py
nanopyfw/examples/jetanalysis.py
nanopyfw-0.0.3.dist-info/LICENSE
nanopyfw-0.0.3.dist-info/METADATA
nanopyfw-0.0.3.dist-info/WHEEL
nanopyfw-0.0.3.dist-info/top_level.txt
nanopyfw-0.0.3.dist-info/RECORD
